bittersweet/__init__.py
bittersweet/models.py
bittersweet/templatetags/__init__.py
bittersweet/templatetags/bittersweet_context_utils.py
bittersweet/templatetags/bittersweet_json.py
bittersweet/templatetags/bittersweet_querystring.py
bittersweet/templatetags/bittersweet_render_inline.py
django_bittersweet-1.0.0.dist-info/DESCRIPTION.rst
django_bittersweet-1.0.0.dist-info/METADATA
django_bittersweet-1.0.0.dist-info/RECORD
django_bittersweet-1.0.0.dist-info/WHEEL
django_bittersweet-1.0.0.dist-info/metadata.json
django_bittersweet-1.0.0.dist-info/top_level.txt
