Metadata-Version: 2.0
Name: django-bittersweet
Version: 1.0.0
Summary: Reusable Django model validation utility
Home-page: https://github.com/acdha/django-bittersweet
Author: Chris Adams
Author-email: chris@improbable.org
License: CC0
Keywords: bittersweet
Platform: UNKNOWN
Classifier: Development Status :: 5 - Production/Stable
Classifier: Framework :: Django
Classifier: Framework :: Django :: 1.8
Classifier: Framework :: Django :: 1.9
Classifier: Intended Audience :: Developers
Classifier: License :: CC0 1.0 Universal (CC0 1.0) Public Domain Dedication
Classifier: Natural Language :: English
Classifier: Programming Language :: Python :: 2
Classifier: Programming Language :: Python :: 2.7
Classifier: Programming Language :: Python :: 3
Classifier: Programming Language :: Python :: 3.4
Classifier: Programming Language :: Python :: 3.5
Requires-Dist: Django
